{
  "e5fce8c2-8ded-41c0-8324-fd0cb46f8b57" : {
    "messageId" : "e5fce8c2-8ded-41c0-8324-fd0cb46f8b57",
    "sendUser" : {
      "userId" : "9fb4c019-659b-41dd-9e1e-898e02940880",
      "userName" : "woody",
      "email" : "woody@codeit.com",
      "phoneNum" : "010-1111-1111",
      "createdAt" : 1737891801188,
      "updatedAt" : 0
    },
    "messageDetail" : "안녕하세요.",
    "createdAt" : 1737891801363,
    "updatedAt" : 0,
    "channel" : {
      "channelId" : "81099b86-592d-4719-b0ca-76fe076175c0",
      "channelName" : "공지",
      "createdAt" : 1737891801361,
      "updatedAt" : 0,
      "users" : {
      }
    }
  }
}